MANIFEST.in
README.txt
setup.py
src/requires.txt
src/m3_mutex/__init__.py
src/m3_mutex/actions.py
src/m3_mutex/api.py
src/m3_mutex/app_meta.py
src/m3_mutex/backends.py
src/m3_mutex/domain.py
src/m3_mutex/exceptions.py
src/m3_mutex/helpers.py
src/m3_mutex/models.py
src/m3_mutex/ui.py
src/m3_mutex/version.py
src/m3_mutex.egg-info/PKG-INFO
src/m3_mutex.egg-info/SOURCES.txt
src/m3_mutex.egg-info/dependency_links.txt
src/m3_mutex.egg-info/top_level.txt
src/m3_mutex/doc/Makefile
src/m3_mutex/doc/make.bat
src/m3_mutex/doc/build/doctrees/basic.doctree
src/m3_mutex/doc/build/doctrees/common.doctree
src/m3_mutex/doc/build/doctrees/environment.pickle
src/m3_mutex/doc/build/doctrees/example.doctree
src/m3_mutex/doc/build/doctrees/index.doctree
src/m3_mutex/doc/build/doctrees/installation.doctree
src/m3_mutex/doc/build/html/.buildinfo
src/m3_mutex/doc/build/html/basic.html
src/m3_mutex/doc/build/html/common.html
src/m3_mutex/doc/build/html/example.html
src/m3_mutex/doc/build/html/genindex.html
src/m3_mutex/doc/build/html/index.html
src/m3_mutex/doc/build/html/installation.html
src/m3_mutex/doc/build/html/objects.inv
src/m3_mutex/doc/build/html/search.html
src/m3_mutex/doc/build/html/searchindex.js
src/m3_mutex/doc/build/html/_images/classes.png
src/m3_mutex/doc/build/html/_sources/basic.txt
src/m3_mutex/doc/build/html/_sources/common.txt
src/m3_mutex/doc/build/html/_sources/example.txt
src/m3_mutex/doc/build/html/_sources/index.txt
src/m3_mutex/doc/build/html/_sources/installation.txt
src/m3_mutex/doc/build/html/_static/ajax-loader.gif
src/m3_mutex/doc/build/html/_static/basic.css
src/m3_mutex/doc/build/html/_static/classes.png
src/m3_mutex/doc/build/html/_static/comment-bright.png
src/m3_mutex/doc/build/html/_static/comment-close.png
src/m3_mutex/doc/build/html/_static/comment.png
src/m3_mutex/doc/build/html/_static/default.css
src/m3_mutex/doc/build/html/_static/doctools.js
src/m3_mutex/doc/build/html/_static/down-pressed.png
src/m3_mutex/doc/build/html/_static/down.png
src/m3_mutex/doc/build/html/_static/file.png
src/m3_mutex/doc/build/html/_static/jquery.js
src/m3_mutex/doc/build/html/_static/minus.png
