Metadata-Version: 1.1
Name: m3-mutex
Version: 2.0.2
Summary: Работа с семафорами и глобальными локами операций
Home-page: https://bitbucket.org/barsgroup/m3-mutex
Author: BARS Group
Author-email: bars@bars-open.ru
License: MIT
Platform: UNKNOWN
Classifier: Intended Audience :: Developers
Classifier: Environment :: Web Environment
Classifier: Natural Language :: Russian
Classifier: Natural Language :: English
Classifier: Operating System :: OS Independent
Classifier: Programming Language :: Python
Classifier: License :: OSI Approved :: MIT License
Classifier: Development Status :: 5 - Production/Stable
